pyproject.toml
setup.py
alkira/__init__.py
alkira/sdk.py
alkira.egg-info/PKG-INFO
alkira.egg-info/SOURCES.txt
alkira.egg-info/dependency_links.txt
alkira.egg-info/requires.txt
alkira.egg-info/top_level.txt